digicomm/LinearModulator.py
digicomm/Pll.py
digicomm/__init__.py
digicomm/constellations.py
digicomm-0.0.3.dist-info/LICENSE
digicomm-0.0.3.dist-info/METADATA
digicomm-0.0.3.dist-info/WHEEL
digicomm-0.0.3.dist-info/top_level.txt
digicomm-0.0.3.dist-info/RECORD
