Metadata-Version: 2.1
Name: digicomm
Version: 0.0.3
Summary: Tools for digital communications simulations
Home-page: https://github.com/ae6nr/digicomm
Author: Bryan Redd
Author-email: bryan.d.redd@gmail.com
License: UNKNOWN
Project-URL: About Me, https://ae6nr.github.io/
Project-URL: Bug Tracker, https://github.com/ae6nr/digicomm/issues
Platform: UNKNOWN
Classifier: Programming Language :: Python :: 3
Classifier: License :: OSI Approved :: MIT License
Classifier: Operating System :: OS Independent
Requires-Python: >=3.6
License-File: LICENSE
